textdatasetcleaner/__init__.py
textdatasetcleaner/cli.py
textdatasetcleaner/exceptions.py
textdatasetcleaner/helpers.py
textdatasetcleaner/loaders.py
textdatasetcleaner/validators.py
textdatasetcleaner/processors/__init__.py
textdatasetcleaner/processors/add_postfix.py
textdatasetcleaner/processors/add_prefix.py
textdatasetcleaner/processors/base.py
textdatasetcleaner/processors/clean_html.py
textdatasetcleaner/processors/clean_symbols.py
textdatasetcleaner/processors/detect_language.py
textdatasetcleaner/processors/filter_currency_symbols.py
textdatasetcleaner/processors/filter_email.py
textdatasetcleaner/processors/filter_emoji.py
textdatasetcleaner/processors/filter_hashtags.py
textdatasetcleaner/processors/filter_max_length.py
textdatasetcleaner/processors/filter_min_length.py
textdatasetcleaner/processors/filter_numbers.py
textdatasetcleaner/processors/filter_phone_number.py
textdatasetcleaner/processors/filter_stop_words.py
textdatasetcleaner/processors/filter_url.py
textdatasetcleaner/processors/filter_user_handle.py
textdatasetcleaner/processors/line_convert_case.py
textdatasetcleaner/processors/line_strip.py
textdatasetcleaner/processors/normalize_hyphenated_words.py
textdatasetcleaner/processors/normalize_quotation_marks.py
textdatasetcleaner/processors/normalize_repeating_chars.py
textdatasetcleaner/processors/normalize_unicode.py
textdatasetcleaner/processors/normalize_whitespace.py
textdatasetcleaner/processors/remove_accents.py
textdatasetcleaner/processors/remove_profanity.py
textdatasetcleaner/processors/shuffle.py
textdatasetcleaner/processors/unique.py
textdatasetcleaner-0.0.6.dist-info/LICENSE
textdatasetcleaner-0.0.6.dist-info/METADATA
textdatasetcleaner-0.0.6.dist-info/WHEEL
textdatasetcleaner-0.0.6.dist-info/entry_points.txt
textdatasetcleaner-0.0.6.dist-info/top_level.txt
textdatasetcleaner-0.0.6.dist-info/RECORD
