Metadata-Version: 2.1
Name: textdatasetcleaner
Version: 0.0.6
Summary: Pipeline for cleaning (preprocessing/normalizing) text datasets
Home-page: https://github.com/TextDatasetCleaner/TextDatasetCleaner
Author: Denis Veselov
License: MIT
Project-URL: Documentation, https://github.com/TextDatasetCleaner/TextDatasetCleaner
Project-URL: Source Code, https://github.com/TextDatasetCleaner/TextDatasetCleaner
Project-URL: Bug Tracker, https://github.com/TextDatasetCleaner/TextDatasetCleaner/issues
Keywords: nlp,preprocessing,text analytics,normalization,natural language processing,linguistics,text processing,text mining
Platform: UNKNOWN
Classifier: Development Status :: 3 - Alpha
Classifier: Intended Audience :: Developers
Classifier: Intended Audience :: Education
Classifier: Intended Audience :: Science/Research
Classifier: License :: OSI Approved :: MIT License
Classifier: Programming Language :: Python
Classifier: Programming Language :: Python :: 3.6
Classifier: Programming Language :: Python :: 3.7
Classifier: Programming Language :: Python :: 3.8
Classifier: Programming Language :: Python :: 3.9
Classifier: Natural Language :: English
Classifier: Topic :: Scientific/Engineering
Classifier: Topic :: Text Processing :: Linguistic
Classifier: Topic :: Software Development :: Libraries
Classifier: Operating System :: POSIX
Classifier: Operating System :: Unix
Classifier: Operating System :: MacOS
Requires-Python: >=3.6
Requires-Dist: srsly (==1.0.2)
Requires-Dist: tqdm (>=4.49.0<5.0.0)
Requires-Dist: scikit-learn (<=0.20.2)
Requires-Dist: profanity-check (==1.0.3)
Requires-Dist: selectolax (<0.3.0,>=0.2.7)
Requires-Dist: requests (<3.0.0,>=2.24.0)
Requires-Dist: click (<8.0.0,>=7.1.2)
Requires-Dist: PyYAML (<6.0.0,>=5.3.1)
Requires-Dist: textacy (>=0.10.1<1.0.0)
Requires-Dist: fasttext (==0.9.2)
